{
  "artist": "Arashi",
  "song": "Tsunagu",
  "lyrics": "誰だってそう探してるEveryday<br/>\n<i>Dare datte sou sagashiteru Everyday</i><br/>\nEs así para todo el mundo, cada día estamos buscando<br/>\n<br/>\n彷徨い歩いて幸せの場所まで<br/>\n<i>Samayoi aruite shiawase no basho made</i><br/>\nCaminando sin rumbo hacia el lugar de la felicidad<br/>\n<br/>\nWhy? 何か起きるサイン<br/>\n<i>Why? Nanika okiru sain</i><br/>\n¿Por qué? La señal de que algo va a pasar<br/>\n<br/>\n矛盾も超えて引き寄せたこの運命<br/>\n<i>Mujun mo koete hikiyoseta kono unmei</i><br/>\nAtrapa el destino más allá de lo imposible<br/>\n<br/>\n強がってるフリをして危うく揺れる<br/>\n<i>Tsuyogatteru furi wo shite ayauku yureru</i><br/>\nFingiendo ser fuerte, temblando peligrosamente<br/>\n<br/>\n心配ならいらないよ守り抜くから<br/>\n<i>Shinpai nara iranaiyo mamori nukukara</i><br/>\nNo tienes de qué preocuparte, porque te protegeré<br/>\n<br/>\n何があっても<br/>\n<i>Nani ga attemo</i><br/>\nPase lo que pase<br/>\n<br/>\nどんな暗い夜でもあなただけを奪い去るから<br/>\n<i>Donna kurai yoru demo anata dake wo ubaisaru kara</i><br/>\nPor muy oscura que sea la noche, sólo a ti te llevaré conmigo<br/>\n<br/>\n<i>Oh! Never let you go</i><br/>\n¡Oh! Nunca te dejaré ir<br/>\n<br/>\n遠慮なんかしないぜ魅せられたら音も立てずに<br/>\n<i>Enryo nanka shinaize miseraretara otomo tatezuni</i><br/>\nSi estás fascinada, no te contengas, sin hacer ruido<br/>\n<br/>\n<i>Don't wanna let you go</i><br/>\nNo quiero dejarte marchar<br/>\n<br/>\n偽りだらけの浮世でもこの愛だけ信じていて<br/>\n<i>Itsuwari darake no ukiyodemo kono ai dake shinjiteite</i><br/>\nAunque ésta sea una vida fugaz llena de mentiras, tan sólo cree en este amor<br/>\n<br/>\nどこにあるか分からないけど楽園を夢見た<br/>\n<i>Doko ni aruka wakaranai kedo rakuen wo yume mita</i><br/>\nSoñé con un paraíso en un lugar desconocido<br/>\n<br/>\n消えないでLove<br/>\n<i>Kienaide Love</i><br/>\nNo desaparezcas, amor<br/>\n<br/>\n絡まってもう解けないモノ<br/>\n<i>Karamatte mou hodokedanai mono</i><br/>\nLos enredos que no se pueden deshacer<br/>\n<br/>\n追うほど辛い知らぬフリできない<br/>\n<i>Ouhodo tsurai shiranu furi dekinai</i><br/>\nCuanto más lo persigues, más te duele, no puedes fingir que no lo sabes<br/>\n<br/>\nそう中途半端なまやかしの人生はNo No　<br/>\n<i>Sou chuuto hanpana mayakashi no jinsei wa no no</i><br/>\nEso es, no quiero una vida con engaños a medias, no, no<br/>\n<br/>\n痛みも飲み込んで<br/>\n<i>Itami mo nomikonde</i><br/>\nSuperaré incluso el dolor<br/>\n<br/>\n無常に漂うMy life 教えてくれた<br/>\n<i>Mujou ni tadayou my life oshiete kureta</i><br/>\nEsta vida que flota fugaz me lo enseñó<br/>\n<br/>\n本当の優しさと強さ求めて行き着くまで<br/>\n<i>Hontou no yasashisa to tsuyosa motomete ikitsuku made</i><br/>\nPersigue la verdadera bondad y fuerza hasta que la alcances<br/>\n<br/>\n移ろいゆく世に輝いては心奪われ<br/>\n<i>Usturoi yuku yoni kagayaite wa kokoro ubaware</i><br/>\nEn este mundo incierto, atrapará tu corazón al brillar<br/>\n<br/>\n<i>Oh! Never let you go</i><br/>\n¡Oh! Nunca te dejaré ir <br/>\n<br/>\n真っすぐな瞳に導かれて声にならない<br/>\n<i>Maasugu na hitomi ni michibikarete koe ni naranai</i><br/>\nGuiado por tu mirada honesta, sin decir una palabra<br/>\n<br/>\n<i>Don't wanna let you go</i><br/>\nNo quiero dejarte marchar<br/>\n<br/>\n巡り巡る時代の中でかけがえない愛のため<br/>\n<i>Meguri meguru jidai no naka de kakegaenai ai no tame</i><br/>\nEn las épocas que vienen y van, por un amor irreemplazable<br/>\n<br/>\nたとえ別れが来たとしてもあの時誓った約束はLove<br/>\n<i>Tatoe wakare ga kita toshitemo ano toki chikatta yakusoku wa love</i><br/>\nAunque pueda llegar la despedida, aquel día nos prometimos amor<br/>\n<br/>\n“One day, One way, One time... どこまで”<br/>\n<i>One day, One way, One time... doko made</i><br/>\nUn día, un camino, una vez... Hasta dónde<br/>\n<br/>\n&nbsp;“One day, One way, One time... 続くの”<br/>\n<i>One day, One way, One time... tsudzuku no</i><br/>\nUn día, un camino, una vez... Seguiremos<br/>\n<br/>\n“One day, One way, One time... 教えて”<br/>\n<i>One day, One way, One time... Oshiete</i><br/>\nUn día, un camino, una vez...&nbsp; Dímelo<br/>\n<br/>\n振り向かずに生きてくだけ<br/>\n<i>Furimukazuni ikiteku dake</i><br/>\nSin mirar atrás, simplemente viviendo<br/>\n<br/>\nどんな暗い夜でもあなただけを奪い去るから<br/>\n<i>Donna kurai yoru demo anata dake wo ubaisaru kara</i><br/>\nPor muy oscura que sea la noche, sólo a ti te llevaré conmigo<br/>\n<br/>\n<i>Oh! Never let you go</i><br/>\n¡Oh! Nunca te dejaré ir<br/>\n<br/>\n遠慮なんかしないぜ魅せられたら音も立てずに<br/>\n<i>Enryo nanka shinaize miseraretara otomo tatezuni</i><br/>\nSi estás fascinada, no te contengas, sin hacer ruido<br/>\n<br/>\n<i>Don't wanna let you go</i><br/>\nNo quiero dejarte marchar<br/>\n<br/>\n偽りだらけの浮世でもこの愛だけ信じていて<br/>\n<i>Itsuwari darake no ukiyodemo kono ai dake shinjiteite</i><br/>\nAunque ésta sea una vida fugaz llena de mentiras, tan sólo cree en este amor<br/>\n<br/>\nどこにあるか分からないけど楽園を夢見た<br/>\n<i>Doko ni aruka wakaranai kedo rakuen wo yume mita</i><br/>\nSoñé con un paraíso en un lugar desconocido<br/>\n<br/>\n消えないでLove<br/>\n<i>Kienaide Love</i><br/>\nNo desaparezcas, amor<br/>\n<br/>",
  "info": "<b>Créditos:</b><br/>\n\nLetra en japonés y traducción al coreano: <a href=\"http://blog.naver.com/PostView.nhn?blogId=jample&amp;logNo=221039771636\" target=\"_blank\">Jample</a>.<br/>\n\nRomaji: Yasashii Uta a partir de Jample.<br/>\n\nTraducción al inglés (versión corta):  <a href=\"https://onelovearashi.tumblr.com/post/162167432960/tsunagu-music-station-ver-translations\" target=\"_blank\">One love Arashi (Tumblr)</a>.*<br/>\n\nTraducción al español: Yasashii Uta.<br/>\n\n<br/>\n\n*No he encontrado traducción de la canción completa al inglés, así que he tenido que hacer una parte a partir de la traducción coreana y de lo que entendía de la letra original, así que puede que no sea la más correcta. Espero que aun así sea útil.",
  "blogger_link": "/2017/07/letra-arashi-tsunagu.html"
}